loggingdecorators/__init__.py
loggingdecorators/__main__.py
loggingdecorators/decorators.py
loggingdecorators-0.1.3.dist-info/LICENSE
loggingdecorators-0.1.3.dist-info/METADATA
loggingdecorators-0.1.3.dist-info/WHEEL
loggingdecorators-0.1.3.dist-info/top_level.txt
loggingdecorators-0.1.3.dist-info/RECORD
