Metadata-Version: 2.1
Name: loggingdecorators
Version: 0.1.3
Summary: NONE
Home-page: https://github.com/adamtuft/loggingdecorators
Author: Adam Tuft
Author-email: adam.s.tuft@gmail.com
License: UNKNOWN
Platform: linux
License-File: LICENSE
